beautifyPlot/__init__.py
beautifyPlot/bplt.py
beautifyPlot-0.2.dist-info/LICENSE
beautifyPlot-0.2.dist-info/METADATA
beautifyPlot-0.2.dist-info/WHEEL
beautifyPlot-0.2.dist-info/top_level.txt
beautifyPlot-0.2.dist-info/RECORD
