Metadata-Version: 2.1
Name: beautifyPlot
Version: 0.2
Summary: A simple matplotlib wrapper to avoid writing multiple plt. statements.
Author-email: "Keerthi Vasan G.C." <kvch@ucdavis.edu>
Project-URL: Homepage, https://github.com/kvgc/beautifyPlot
Project-URL: Issues, https://github.com/kvgc/beautifyPlot/issues
Classifier: Programming Language :: Python :: 3
Classifier: License :: OSI Approved :: MIT License
Classifier: Operating System :: OS Independent
Requires-Python: >=3.8
License-File: LICENSE
